pybuilder_stubs_package/__init__.py
pybuilder_stubs_package-0.1.3.dist-info/METADATA
pybuilder_stubs_package-0.1.3.dist-info/WHEEL
pybuilder_stubs_package-0.1.3.dist-info/namespace_packages.txt
pybuilder_stubs_package-0.1.3.dist-info/top_level.txt
pybuilder_stubs_package-0.1.3.dist-info/zip-safe
pybuilder_stubs_package-0.1.3.dist-info/RECORD
