Metadata-Version: 2.1
Name: pybuilder-stubs-package
Version: 0.1.3
Summary: PyBuilder plugin that creates "*-stubs" package for your project using MyPy's stubgen
Home-page: https://github.com/chylek/pybuilder-stubs-package
Author: =?utf-8?q?Adam_Ch=C3=BDlek?=
Author-email: adam.chylek@amitia-ai.com
Maintainer: 
Maintainer-email: 
License: MIT
Classifier: Development Status :: 3 - Alpha
Classifier: License :: OSI Approved :: MIT License
Classifier: Programming Language :: Python :: 3
